gnews/__init__.py
gnews/gnews.py
gnews/utils/__init__.py
gnews/utils/constants.py
gnews/utils/utils.py
gnews-0.3.7.dist-info/LICENSE.txt
gnews-0.3.7.dist-info/METADATA
gnews-0.3.7.dist-info/WHEEL
gnews-0.3.7.dist-info/top_level.txt
gnews-0.3.7.dist-info/RECORD
