Metadata-Version: 2.1
Name: gnews
Version: 0.3.7
Summary: Provide an API to search for articles on Google News and returns a usable JSON response.
Home-page: https://github.com/ranahaani/GNews/
Author: Muhammad Abdullah
Author-email: ranahaani@gmail.com
Project-URL: Documentation, https://github.com/ranahaani/GNews/blob/master/README.md
Project-URL: Source, https://github.com/ranahaani/GNews/
Project-URL: Tracker, https://github.com/ranahaani/GNews/issues
Classifier: Development Status :: 5 - Production/Stable
Classifier: Intended Audience :: Developers
Classifier: Programming Language :: Python :: 3
Classifier: Programming Language :: Python :: 3.8
Classifier: Programming Language :: Python :: 3.9
Classifier: Programming Language :: Python :: 3.10
Classifier: Programming Language :: Python :: 3.11
Classifier: License :: OSI Approved :: MIT License
Classifier: Operating System :: OS Independent
License-File: LICENSE.txt
Requires-Dist: feedparser ~=6.0.2
Requires-Dist: beautifulsoup4 <5,>=4.9.3
Requires-Dist: dnspython ~=1.16.0
Requires-Dist: requests
